.gitignore
LICENSE
README.md
__init__.py
pyproject.toml
requirements.txt
setup.cfg
setup.py
src/pyland.py
src/_pyland/__init__.py
src/_pyland/_version.py
src/_pyland/assert.py
src/_pyland/cases_collect.py
src/_pyland/cases_execute.py
src/_pyland/cmd.py
src/_pyland/config.py
src/_pyland/exceptions.py
src/_pyland/extractor.py
src/_pyland/log.py
src/_pyland/pre_request.py
src/_pyland/pytest_run.py
src/_pyland/scaffold.py
src/_pyland/sql.py
src/_pyland/api/__init__.py
src/_pyland/api/api_case.py
src/_pyland/api/api_test.py
src/_pyland/api/main.py
src/_pyland/api/run.py
src/_pyland/commands/__init__.py
src/_pyland/commands/init.py
src/_pyland/commands/platform.py
src/_pyland/commands/server.py
src/_pyland/scripts/__init__.py
src/_pyland/scripts/conftest.py
src/_pyland/scripts/main.py
src/_pyland/scripts/run.py
src/_pyland/thirdparty/__init__.py
src/_pyland/thirdparty/case_manage.py
src/_pyland/thirdparty/group_manage.py
src/_pyland/thirdparty/project_manage.py
src/_pyland/thirdparty/result_manage.py
src/_pyland/utils/__init__.py
src/_pyland/utils/allure_opt.py
src/_pyland/utils/api.py
src/_pyland/utils/assertion.py
src/_pyland/utils/client.py
src/_pyland/utils/common_argv.py
src/_pyland/utils/error.py
src/_pyland/utils/file_reader.py
src/_pyland/utils/file_writer.py
src/_pyland/utils/generator.py
src/_pyland/utils/http_case.py
src/_pyland/utils/injson.py
src/_pyland/utils/playground.py
src/_pyland/utils/responses.py
src/_pyland/utils/support.py
src/_pyland/utils/swagger_api.py
src/_pyland/utils/tables_query.py
src/pyland.egg-info/PKG-INFO
src/pyland.egg-info/SOURCES.txt
src/pyland.egg-info/dependency_links.txt
src/pyland.egg-info/entry_points.txt
src/pyland.egg-info/not-zip-safe
src/pyland.egg-info/requires.txt
src/pyland.egg-info/top_level.txt