Metadata-Version: 2.1
Name: pyland
Version: 0.2.33
Summary: based on pytest to create test framework automatically
Home-page: https://docs.pyland.org/en/latest/
Author: Jiukun
License: UNKNOWN
Project-URL: Changelog, https://docs.pytest.org/en/stable/changelog.html
Project-URL: Twitter, https://twitter.com/pytestdotorg
Project-URL: Source, https://github.com/pytest-dev/pytest
Project-URL: Tracker, https://github.com/pytest-dev/pytest/issues
Platform: UNKNOWN
Classifier: Programming Language :: Python :: 3.7
Classifier: License :: OSI Approved :: MIT License
Classifier: Operating System :: OS Independent
Requires-Python: !=3.0.*,!=3.1.*,!=3.2.*,!=3.3.*,>=2.7
License-File: LICENSE
